{"album": {"album_type": "album", "artists": [{"external_urls": {"spotify": "https://open.spotify.com/artist/4wo1267SJuUfHgasdlfNfc"}, "href": "https://api.spotify.com/v1/artists/4wo1267SJuUfHgasdlfNfc", "id": "4wo1267SJuUfHgasdlfNfc", "name": "The Raconteurs", "type": "artist", "uri": "spotify:artist:4wo1267SJuUfHgasdlfNfc"}], "available_markets": [], "external_urls": {"spotify": "https://open.spotify.com/album/7pHR5BTXW3JfBPUBjtjRKX"}, "href": "https://api.spotify.com/v1/albums/7pHR5BTXW3JfBPUBjtjRKX", "id": "7pHR5BTXW3JfBPUBjtjRKX", "images": [{"url": "https://i.scdn.co/image/ab67616d0000b273f95c49bade9e902dfd0fda67", "width": 640, "height": 640}, {"url": "https://i.scdn.co/image/ab67616d00001e02f95c49bade9e902dfd0fda67", "width": 300, "height": 300}, {"url": "https://i.scdn.co/image/ab67616d00004851f95c49bade9e902dfd0fda67", "width": 64, "height": 64}], "name": "Consolers of the Lonely", "release_date": "2008-03-25", "release_date_precision": "day", "total_tracks": 14, "type": "album", "uri": "spotify:album:7pHR5BTXW3JfBPUBjtjRKX"}, "artists": [{"external_urls": {"spotify": "https://open.spotify.com/artist/4wo1267SJuUfHgasdlfNfc"}, "href": "https://api.spotify.com/v1/artists/4wo1267SJuUfHgasdlfNfc", "id": "4wo1267SJuUfHgasdlfNfc", "name": "The Raconteurs", "type": "artist", "uri": "spotify:artist:4wo1267SJuUfHgasdlfNfc"}], "available_markets": [], "disc_number": 1, "duration_ms": 220600, "explicit": false, "external_ids": {"isrc": "GBBKS0800216"}, "external_urls": {"spotify": "https://open.spotify.com/track/2Ndoc3EhEfTzGH4qqIDTj4"}, "href": "https://api.spotify.com/v1/tracks/2Ndoc3EhEfTzGH4qqIDTj4", "id": "2Ndoc3EhEfTzGH4qqIDTj4", "is_local": false, "name": "Attention", "popularity": 0, "preview_url": null, "track_number": 10, "type": "track", "uri": "spotify:track:2Ndoc3EhEfTzGH4qqIDTj4"}