{"album": {"album_type": "single", "artists": [{"external_urls": {"spotify": "https://open.spotify.com/artist/0HS00NN7MAfF59aJnfcxSO"}, "href": "https://api.spotify.com/v1/artists/0HS00NN7MAfF59aJnfcxSO", "id": "0HS00NN7MAfF59aJnfcxSO", "name": "Stephanie Poetri", "type": "artist", "uri": "spotify:artist:0HS00NN7MAfF59aJnfcxSO"}], "available_markets": [], "external_urls": {"spotify": "https://open.spotify.com/album/3KmwObuD2kb4XcuUnMJkQ7"}, "href": "https://api.spotify.com/v1/albums/3KmwObuD2kb4XcuUnMJkQ7", "id": "3KmwObuD2kb4XcuUnMJkQ7", "images": [{"url": "https://i.scdn.co/image/ab67616d0000b273ee07f5d93ce85ea2013fc959", "width": 640, "height": 640}, {"url": "https://i.scdn.co/image/ab67616d00001e02ee07f5d93ce85ea2013fc959", "width": 300, "height": 300}, {"url": "https://i.scdn.co/image/ab67616d00004851ee07f5d93ce85ea2013fc959", "width": 64, "height": 64}], "name": "Do You Love Me", "release_date": "2020-02-14", "release_date_precision": "day", "total_tracks": 2, "type": "album", "uri": "spotify:album:3KmwObuD2kb4XcuUnMJkQ7"}, "artists": [{"external_urls": {"spotify": "https://open.spotify.com/artist/0HS00NN7MAfF59aJnfcxSO"}, "href": "https://api.spotify.com/v1/artists/0HS00NN7MAfF59aJnfcxSO", "id": "0HS00NN7MAfF59aJnfcxSO", "name": "Stephanie Poetri", "type": "artist", "uri": "spotify:artist:0HS00NN7MAfF59aJnfcxSO"}], "available_markets": [], "disc_number": 1, "duration_ms": 144383, "explicit": false, "external_ids": {"isrc": "ZZOPM2001931"}, "external_urls": {"spotify": "https://open.spotify.com/track/1rbjic9uKr1p6nxnjLDHN6"}, "href": "https://api.spotify.com/v1/tracks/1rbjic9uKr1p6nxnjLDHN6", "id": "1rbjic9uKr1p6nxnjLDHN6", "is_local": false, "name": "Do You Love Me", "popularity": 0, "preview_url": null, "track_number": 1, "type": "track", "uri": "spotify:track:1rbjic9uKr1p6nxnjLDHN6"}