{"album": {"album_type": "album", "artists": [{"external_urls": {"spotify": "https://open.spotify.com/artist/2WXllWJylpBWxIAHHcTEQ0"}, "href": "https://api.spotify.com/v1/artists/2WXllWJylpBWxIAHHcTEQ0", "id": "2WXllWJylpBWxIAHHcTEQ0", "name": "La Base", "type": "artist", "uri": "spotify:artist:2WXllWJylpBWxIAHHcTEQ0"}], "available_markets": [], "external_urls": {"spotify": "https://open.spotify.com/album/3uk3dTZkdV9kTMhxXrwF33"}, "href": "https://api.spotify.com/v1/albums/3uk3dTZkdV9kTMhxXrwF33", "id": "3uk3dTZkdV9kTMhxXrwF33", "images": [{"url": "https://i.scdn.co/image/ab67616d0000b273b9b40dc75227456dd39346cc", "width": 640, "height": 640}, {"url": "https://i.scdn.co/image/ab67616d00001e02b9b40dc75227456dd39346cc", "width": 300, "height": 300}, {"url": "https://i.scdn.co/image/ab67616d00004851b9b40dc75227456dd39346cc", "width": 64, "height": 64}], "name": "Inimitable (En Vivo)", "release_date": "2004-01-13", "release_date_precision": "day", "total_tracks": 22, "type": "album", "uri": "spotify:album:3uk3dTZkdV9kTMhxXrwF33"}, "artists": [{"external_urls": {"spotify": "https://open.spotify.com/artist/2WXllWJylpBWxIAHHcTEQ0"}, "href": "https://api.spotify.com/v1/artists/2WXllWJylpBWxIAHHcTEQ0", "id": "2WXllWJylpBWxIAHHcTEQ0", "name": "La Base", "type": "artist", "uri": "spotify:artist:2WXllWJylpBWxIAHHcTEQ0"}], "available_markets": [], "disc_number": 1, "duration_ms": 254332, "explicit": false, "external_ids": {"isrc": "ARG601010300"}, "external_urls": {"spotify": "https://open.spotify.com/track/50dk1i4AbqdR2S72uXO3PH"}, "href": "https://api.spotify.com/v1/tracks/50dk1i4AbqdR2S72uXO3PH", "id": "50dk1i4AbqdR2S72uXO3PH", "is_local": false, "name": "Vienes y Te Vas - En Vivo", "popularity": 0, "preview_url": null, "track_number": 10, "type": "track", "uri": "spotify:track:50dk1i4AbqdR2S72uXO3PH"}