{"album": {"album_type": "single", "artists": [{"external_urls": {"spotify": "https://open.spotify.com/artist/0nTErwSOllrcUWt3knOG2T"}, "href": "https://api.spotify.com/v1/artists/0nTErwSOllrcUWt3knOG2T", "id": "0nTErwSOllrcUWt3knOG2T", "name": "Jazzanova", "type": "artist", "uri": "spotify:artist:0nTErwSOllrcUWt3knOG2T"}, {"external_urls": {"spotify": "https://open.spotify.com/artist/01e2lCvLZ4fLUIRy68nptH"}, "href": "https://api.spotify.com/v1/artists/01e2lCvLZ4fLUIRy68nptH", "id": "01e2lCvLZ4fLUIRy68nptH", "name": "Wankelmut", "type": "artist", "uri": "spotify:artist:01e2lCvLZ4fLUIRy68nptH"}], "available_markets": [], "external_urls": {"spotify": "https://open.spotify.com/album/4Lvs8WckE3omqT7TdK7tH9"}, "href": "https://api.spotify.com/v1/albums/4Lvs8WckE3omqT7TdK7tH9", "id": "4Lvs8WckE3omqT7TdK7tH9", "images": [{"url": "https://i.scdn.co/image/ab67616d0000b273ff5800086ff70205d3e29bed", "width": 640, "height": 640}, {"url": "https://i.scdn.co/image/ab67616d00001e02ff5800086ff70205d3e29bed", "width": 300, "height": 300}, {"url": "https://i.scdn.co/image/ab67616d00004851ff5800086ff70205d3e29bed", "width": 64, "height": 64}], "name": "Follow Your Feet (Wankelmut Remix)", "release_date": "2018-11-09", "release_date_precision": "day", "total_tracks": 2, "type": "album", "uri": "spotify:album:4Lvs8WckE3omqT7TdK7tH9"}, "artists": [{"external_urls": {"spotify": "https://open.spotify.com/artist/0nTErwSOllrcUWt3knOG2T"}, "href": "https://api.spotify.com/v1/artists/0nTErwSOllrcUWt3knOG2T", "id": "0nTErwSOllrcUWt3knOG2T", "name": "Jazzanova", "type": "artist", "uri": "spotify:artist:0nTErwSOllrcUWt3knOG2T"}, {"external_urls": {"spotify": "https://open.spotify.com/artist/7c59lOg1veety7jD83d31w"}, "href": "https://api.spotify.com/v1/artists/7c59lOg1veety7jD83d31w", "id": "7c59lOg1veety7jD83d31w", "name": "Pete Josef", "type": "artist", "uri": "spotify:artist:7c59lOg1veety7jD83d31w"}, {"external_urls": {"spotify": "https://open.spotify.com/artist/01e2lCvLZ4fLUIRy68nptH"}, "href": "https://api.spotify.com/v1/artists/01e2lCvLZ4fLUIRy68nptH", "id": "01e2lCvLZ4fLUIRy68nptH", "name": "Wankelmut", "type": "artist", "uri": "spotify:artist:01e2lCvLZ4fLUIRy68nptH"}], "available_markets": [], "disc_number": 1, "duration_ms": 222480, "explicit": false, "external_ids": {"isrc": "DEP961800040"}, "external_urls": {"spotify": "https://open.spotify.com/track/6DgHwjflvz7RAFAIpmjaau"}, "href": "https://api.spotify.com/v1/tracks/6DgHwjflvz7RAFAIpmjaau", "id": "6DgHwjflvz7RAFAIpmjaau", "is_local": false, "name": "Follow Your Feet - Wankelmut Remix", "popularity": 0, "preview_url": null, "track_number": 1, "type": "track", "uri": "spotify:track:6DgHwjflvz7RAFAIpmjaau"}