{"album": {"album_type": "single", "artists": [{"external_urls": {"spotify": "https://open.spotify.com/artist/5fJsY7afrbsyzJj9wdzJMh"}, "href": "https://api.spotify.com/v1/artists/5fJsY7afrbsyzJj9wdzJMh", "id": "5fJsY7afrbsyzJj9wdzJMh", "name": "Tito \"El Bambino\"", "type": "artist", "uri": "spotify:artist:5fJsY7afrbsyzJj9wdzJMh"}], "available_markets": [], "external_urls": {"spotify": "https://open.spotify.com/album/7oUD148tzId9bTUHEha9Co"}, "href": "https://api.spotify.com/v1/albums/7oUD148tzId9bTUHEha9Co", "id": "7oUD148tzId9bTUHEha9Co", "images": [{"url": "https://i.scdn.co/image/ab67616d0000b273abff6f55bb7b2c23266311e0", "width": 640, "height": 640}, {"url": "https://i.scdn.co/image/ab67616d00001e02abff6f55bb7b2c23266311e0", "width": 300, "height": 300}, {"url": "https://i.scdn.co/image/ab67616d00004851abff6f55bb7b2c23266311e0", "width": 64, "height": 64}], "name": "Adicto a Tus Redes (feat. Nicky Jam)", "release_date": "2014-11-18", "release_date_precision": "day", "total_tracks": 1, "type": "album", "uri": "spotify:album:7oUD148tzId9bTUHEha9Co"}, "artists": [{"external_urls": {"spotify": "https://open.spotify.com/artist/5fJsY7afrbsyzJj9wdzJMh"}, "href": "https://api.spotify.com/v1/artists/5fJsY7afrbsyzJj9wdzJMh", "id": "5fJsY7afrbsyzJj9wdzJMh", "name": "Tito \"El Bambino\"", "type": "artist", "uri": "spotify:artist:5fJsY7afrbsyzJj9wdzJMh"}, {"external_urls": {"spotify": "https://open.spotify.com/artist/1SupJlEpv7RS2tPNRaHViT"}, "href": "https://api.spotify.com/v1/artists/1SupJlEpv7RS2tPNRaHViT", "id": "1SupJlEpv7RS2tPNRaHViT", "name": "Nicky Jam", "type": "artist", "uri": "spotify:artist:1SupJlEpv7RS2tPNRaHViT"}], "available_markets": [], "disc_number": 1, "duration_ms": 197346, "explicit": false, "external_ids": {"isrc": "TCACB1483243"}, "external_urls": {"spotify": "https://open.spotify.com/track/7nfsGFrr9yt6dt5YnHOB91"}, "href": "https://api.spotify.com/v1/tracks/7nfsGFrr9yt6dt5YnHOB91", "id": "7nfsGFrr9yt6dt5YnHOB91", "is_local": false, "name": "Adicto a Tus Redes (feat. Nicky Jam)", "popularity": 0, "preview_url": null, "track_number": 1, "type": "track", "uri": "spotify:track:7nfsGFrr9yt6dt5YnHOB91"}