{"album": {"album_type": "single", "artists": [{"external_urls": {"spotify": "https://open.spotify.com/artist/2fVW2ix4ANKiofDZIsy1XR"}, "href": "https://api.spotify.com/v1/artists/2fVW2ix4ANKiofDZIsy1XR", "id": "2fVW2ix4ANKiofDZIsy1XR", "name": "Vargas & Lagola", "type": "artist", "uri": "spotify:artist:2fVW2ix4ANKiofDZIsy1XR"}], "available_markets": [], "external_urls": {"spotify": "https://open.spotify.com/album/1TBr6GN5yvsNqPNlhgXvsf"}, "href": "https://api.spotify.com/v1/albums/1TBr6GN5yvsNqPNlhgXvsf", "id": "1TBr6GN5yvsNqPNlhgXvsf", "images": [{"url": "https://i.scdn.co/image/ab67616d0000b273490f5f52598c73eb1efa5d2f", "width": 640, "height": 640}, {"url": "https://i.scdn.co/image/ab67616d00001e02490f5f52598c73eb1efa5d2f", "width": 300, "height": 300}, {"url": "https://i.scdn.co/image/ab67616d00004851490f5f52598c73eb1efa5d2f", "width": 64, "height": 64}], "name": "Roads", "release_date": "2018-02-09", "release_date_precision": "day", "total_tracks": 1, "type": "album", "uri": "spotify:album:1TBr6GN5yvsNqPNlhgXvsf"}, "artists": [{"external_urls": {"spotify": "https://open.spotify.com/artist/2fVW2ix4ANKiofDZIsy1XR"}, "href": "https://api.spotify.com/v1/artists/2fVW2ix4ANKiofDZIsy1XR", "id": "2fVW2ix4ANKiofDZIsy1XR", "name": "Vargas & Lagola", "type": "artist", "uri": "spotify:artist:2fVW2ix4ANKiofDZIsy1XR"}], "available_markets": [], "disc_number": 1, "duration_ms": 234680, "explicit": false, "external_ids": {"isrc": "SEUM71700963"}, "external_urls": {"spotify": "https://open.spotify.com/track/7CBH8BzH23SksBR5NSb7tT"}, "href": "https://api.spotify.com/v1/tracks/7CBH8BzH23SksBR5NSb7tT", "id": "7CBH8BzH23SksBR5NSb7tT", "is_local": false, "name": "Roads", "popularity": 0, "preview_url": null, "track_number": 1, "type": "track", "uri": "spotify:track:7CBH8BzH23SksBR5NSb7tT"}