{"album": {"album_type": "album", "artists": [{"external_urls": {"spotify": "https://open.spotify.com/artist/5Fv0DQ1ZBuc2DlidtOUCZr"}, "href": "https://api.spotify.com/v1/artists/5Fv0DQ1ZBuc2DlidtOUCZr", "id": "5Fv0DQ1ZBuc2DlidtOUCZr", "name": "Loquillo", "type": "artist", "uri": "spotify:artist:5Fv0DQ1ZBuc2DlidtOUCZr"}], "available_markets": ["AR", "AU", "AT", "BE", "BO", "BR", "BG", "CA", "CL", "CO", "CR", "CY", "CZ", "DK", "DO", "DE", "EC", "EE", "SV", "FI", "FR", "GR", "GT", "HN", "HK", "HU", "IS", "IE", "IT", "LV", "LT", "LU", "MY", "MT", "MX", "NL", "NZ", "NI", "NO", "PA", "PY", "PE", "PH", "PL", "PT", "SG", "SK", "ES", "SE", "CH", "TW", "TR", "UY", "US", "GB", "AD", "LI", "MC", "ID", "JP", "TH", "VN", "RO", "IL", "ZA", "SA", "AE", "BH", "QA", "OM", "KW", "EG", "MA", "DZ", "TN", "LB", "JO", "PS", "IN", "BY", "KZ", "MD", "UA", "AL", "BA", "HR", "ME", "MK", "RS", "SI", "KR", "BD", "PK", "LK", "GH", "KE", "NG", "TZ", "UG", "AG", "AM", "BS", "BB", "BZ", "BT", "BW", "BF", "CV", "CW", "DM", "FJ", "GM", "GE", "GD", "GW", "GY", "HT", "JM", "KI", "LS", "LR", "MW", "MV", "ML", "MH", "FM", "NA", "NR", "NE", "PW", "PG", "PR", "WS", "SM", "ST", "SN", "SC", "SL", "SB", "KN", "LC", "VC", "SR", "TL", "TO", "TT", "TV", "VU", "AZ", "BN", "BI", "KH", "CM", "TD", "KM", "GQ", "SZ", "GA", "GN", "KG", "LA", "MO", "MR", "MN", "NP", "RW", "TG", "UZ", "ZW", "BJ", "MG", "MU", "MZ", "AO", "CI", "DJ", "ZM", "CD", "CG", "IQ", "LY", "TJ", "VE", "ET", "XK"], "external_urls": {"spotify": "https://open.spotify.com/album/24fPzeDiySM2lt3pvuLKGR"}, "href": "https://api.spotify.com/v1/albums/24fPzeDiySM2lt3pvuLKGR", "id": "24fPzeDiySM2lt3pvuLKGR", "images": [{"url": "https://i.scdn.co/image/ab67616d0000b273316d57fd601743059e3c3d71", "width": 640, "height": 640}, {"url": "https://i.scdn.co/image/ab67616d00001e02316d57fd601743059e3c3d71", "width": 300, "height": 300}, {"url": "https://i.scdn.co/image/ab67616d00004851316d57fd601743059e3c3d71", "width": 64, "height": 64}], "name": "Rock & Roll Star - 30 a\u00f1os", "release_date": "2009-11-13", "release_date_precision": "day", "total_tracks": 55, "type": "album", "uri": "spotify:album:24fPzeDiySM2lt3pvuLKGR"}, "artists": [{"external_urls": {"spotify": "https://open.spotify.com/artist/4EM1gc21UrYHQ3eal963Xl"}, "href": "https://api.spotify.com/v1/artists/4EM1gc21UrYHQ3eal963Xl", "id": "4EM1gc21UrYHQ3eal963Xl", "name": "Loquillo Y Los Trogloditas", "type": "artist", "uri": "spotify:artist:4EM1gc21UrYHQ3eal963Xl"}, {"external_urls": {"spotify": "https://open.spotify.com/artist/1tZ99AnqyjgrmPwLfGU5eo"}, "href": "https://api.spotify.com/v1/artists/1tZ99AnqyjgrmPwLfGU5eo", "id": "1tZ99AnqyjgrmPwLfGU5eo", "name": "Fito y Fitipaldis", "type": "artist", "uri": "spotify:artist:1tZ99AnqyjgrmPwLfGU5eo"}], "available_markets": ["AR", "AU", "AT", "BE", "BO", "BR", "BG", "CA", "CL", "CO", "CR", "CY", "CZ", "DK", "DO", "DE", "EC", "EE", "SV", "FI", "FR", "GR", "GT", "HN", "HK", "HU", "IS", "IE", "IT", "LV", "LT", "LU", "MY", "MT", "MX", "NL", "NZ", "NI", "NO", "PA", "PY", "PE", "PH", "PL", "PT", "SG", "SK", "ES", "SE", "CH", "TW", "TR", "UY", "US", "GB", "AD", "LI", "MC", "ID", "JP", "TH", "VN", "RO", "IL", "ZA", "SA", "AE", "BH", "QA", "OM", "KW", "EG", "MA", "DZ", "TN", "LB", "JO", "PS", "IN", "BY", "KZ", "MD", "UA", "AL", "BA", "HR", "ME", "MK", "RS", "SI", "KR", "BD", "PK", "LK", "GH", "KE", "NG", "TZ", "UG", "AG", "AM", "BS", "BB", "BZ", "BT", "BW", "BF", "CV", "CW", "DM", "FJ", "GM", "GE", "GD", "GW", "GY", "HT", "JM", "KI", "LS", "LR", "MW", "MV", "ML", "MH", "FM", "NA", "NR", "NE", "PW", "PG", "PR", "WS", "SM", "ST", "SN", "SC", "SL", "SB", "KN", "LC", "VC", "SR", "TL", "TO", "TT", "TV", "VU", "AZ", "BN", "BI", "KH", "CM", "TD", "KM", "GQ", "SZ", "GA", "GN", "KG", "LA", "MO", "MR", "MN", "NP", "RW", "TG", "UZ", "ZW", "BJ", "MG", "MU", "MZ", "AO", "CI", "DJ", "ZM", "CD", "CG", "IQ", "LY", "TJ", "VE", "ET", "XK"], "disc_number": 1, "duration_ms": 158440, "explicit": false, "external_ids": {"isrc": "ES5010500174"}, "external_urls": {"spotify": "https://open.spotify.com/track/6HxXE7KswTQ9vpYNWelGDb"}, "href": "https://api.spotify.com/v1/tracks/6HxXE7KswTQ9vpYNWelGDb", "id": "6HxXE7KswTQ9vpYNWelGDb", "is_local": false, "name": "Luche contra la ley (feat. Fito y Fitipaldis)", "popularity": 12, "preview_url": null, "track_number": 29, "type": "track", "uri": "spotify:track:6HxXE7KswTQ9vpYNWelGDb"}