{"audio_preview_url": "https://podz-content.spotifycdn.com/audio/clips/1sahWJNtRq9XCN0gyZoxwd/clip_294551_354551.mp3", "description": "Juan y Chava hablan en 20 minutos o menos, a la distancia, de una serie o pel\u00edcula en particular, en esta ocasi\u00f3n es la filmograf\u00eda de Tom Cruise. Todo esto mientras toman cerveza.", "duration_ms": 1343817, "explicit": true, "external_urls": {"spotify": "https://open.spotify.com/episode/1KgOoiMr8QChEoKFC2h1ab"}, "href": "https://api.spotify.com/v1/episodes/1KgOoiMr8QChEoKFC2h1ab", "html_description": "<p>Juan y Chava hablan en 20 minutos o menos, a la distancia, de una serie o pel\u00edcula en particular, en esta ocasi\u00f3n es la filmograf\u00eda de Tom Cruise. Todo esto mientras toman cerveza.</p>", "id": "1KgOoiMr8QChEoKFC2h1ab", "images": [{"height": 640, "url": "https://i.scdn.co/image/ab6765630000ba8a40eaee8a05532b0dcd5c8b7f", "width": 640}, {"height": 300, "url": "https://i.scdn.co/image/ab67656300005f1f40eaee8a05532b0dcd5c8b7f", "width": 300}, {"height": 64, "url": "https://i.scdn.co/image/ab6765630000f68d40eaee8a05532b0dcd5c8b7f", "width": 64}], "is_externally_hosted": false, "is_playable": true, "language": "es-MX", "languages": ["es-MX"], "name": "Shots: Tom Cruise.", "release_date": "2020-06-19", "release_date_precision": "day", "show": {"available_markets": ["AD", "AE", "AG", "AL", "AM", "AR", "AT", "AU", "BA", "BB", "BE", "BF", "BG", "BH", "BJ", "BO", "BR", "BS", "BT", "BW", "BZ", "CA", "CH", "CL", "CO", "CR", "CV", "CW", "CY", "CZ", "DE", "DK", "DM", "DO", "DZ", "EC", "EE", "EG", "ES", "FI", "FJ", "FM", "FR", "GB", "GD", "GE", "GH", "GM", "GR", "GT", "GW", "GY", "HK", "HN", "HR", "HT", "HU", "ID", "IE", "IL", "IN", "IS", "IT", "JM", "JO", "JP", "KE", "KI", "KN", "KR", "KW", "LB", "LC", "LI", "LR", "LS", "LT", "LU", "LV", "MA", "MC", "ME", "MG", "MH", "MK", "ML", "MT", "MU", "MV", "MW", "MX", "MY", "MZ", "NA", "NE", "NG", "NI", "NL", "NO", "NR", "NZ", "OM", "PA", "PE", "PG", "PH", "PL", "PR", "PS", "PT", "PW", "PY", "QA", "RO", "RS", "SA", "SB", "SC", "SE", "SG", "SI", "SK", "SL", "SM", "SN", "SR", "ST", "SV", "TH", "TL", "TN", "TO", "TR", "TT", "TV", "TW", "UA", "US", "UY", "VC", "VN", "VU", "WS", "XK", "ZA"], "copyrights": [], "description": "Un Podcast donde junto a Chava, hablamos entre copas sobre cine, televisi\u00f3n y cultura pop. Http://patreon.com/cineyalcohol", "explicit": true, "external_urls": {"spotify": "https://open.spotify.com/show/10uYVlQuP4iDA1tLEdr7jC"}, "href": "https://api.spotify.com/v1/shows/10uYVlQuP4iDA1tLEdr7jC", "html_description": "Un Podcast donde junto a Chava, hablamos entre copas sobre cine, televisi\u00f3n y cultura pop. Http://patreon.com/cineyalcohol", "id": "10uYVlQuP4iDA1tLEdr7jC", "images": [{"height": 640, "url": "https://i.scdn.co/image/ab6765630000ba8a40eaee8a05532b0dcd5c8b7f", "width": 640}, {"height": 300, "url": "https://i.scdn.co/image/ab67656300005f1f40eaee8a05532b0dcd5c8b7f", "width": 300}, {"height": 64, "url": "https://i.scdn.co/image/ab6765630000f68d40eaee8a05532b0dcd5c8b7f", "width": 64}], "is_externally_hosted": false, "languages": ["es-MX"], "media_type": "mixed", "name": "Cine y Alcohol ", "publisher": "Da Comedy", "total_episodes": 636, "type": "show", "uri": "spotify:show:10uYVlQuP4iDA1tLEdr7jC"}, "type": "episode", "uri": "spotify:episode:1KgOoiMr8QChEoKFC2h1ab"}