{"album": {"album_type": "album", "artists": [{"external_urls": {"spotify": "https://open.spotify.com/artist/5gOJTI4TusSENizxhcG7jB"}, "href": "https://api.spotify.com/v1/artists/5gOJTI4TusSENizxhcG7jB", "id": "5gOJTI4TusSENizxhcG7jB", "name": "David Bisbal", "type": "artist", "uri": "spotify:artist:5gOJTI4TusSENizxhcG7jB"}], "available_markets": [], "external_urls": {"spotify": "https://open.spotify.com/album/3NAwGAUFcWaIuRk9aCRoCR"}, "href": "https://api.spotify.com/v1/albums/3NAwGAUFcWaIuRk9aCRoCR", "id": "3NAwGAUFcWaIuRk9aCRoCR", "images": [{"url": "https://i.scdn.co/image/ab67616d0000b273cdf7b21a19af6769b8951b8d", "width": 640, "height": 640}, {"url": "https://i.scdn.co/image/ab67616d00001e02cdf7b21a19af6769b8951b8d", "width": 300, "height": 300}, {"url": "https://i.scdn.co/image/ab67616d00004851cdf7b21a19af6769b8951b8d", "width": 64, "height": 64}], "name": "David Bisbal (International Version)", "release_date": "2006-01-01", "release_date_precision": "day", "total_tracks": 14, "type": "album", "uri": "spotify:album:3NAwGAUFcWaIuRk9aCRoCR"}, "artists": [{"external_urls": {"spotify": "https://open.spotify.com/artist/5gOJTI4TusSENizxhcG7jB"}, "href": "https://api.spotify.com/v1/artists/5gOJTI4TusSENizxhcG7jB", "id": "5gOJTI4TusSENizxhcG7jB", "name": "David Bisbal", "type": "artist", "uri": "spotify:artist:5gOJTI4TusSENizxhcG7jB"}], "available_markets": [], "disc_number": 1, "duration_ms": 211706, "explicit": false, "external_ids": {"isrc": "ES6010200293"}, "external_urls": {"spotify": "https://open.spotify.com/track/70iXrOETHNdFJpEikr4h2C"}, "href": "https://api.spotify.com/v1/tracks/70iXrOETHNdFJpEikr4h2C", "id": "70iXrOETHNdFJpEikr4h2C", "is_local": false, "name": "Ave Mar\u00eda", "popularity": 0, "preview_url": null, "track_number": 13, "type": "track", "uri": "spotify:track:70iXrOETHNdFJpEikr4h2C"}