{"album": {"album_type": "album", "artists": [{"external_urls": {"spotify": "https://open.spotify.com/artist/3ZJhC6cKBtTx6jUJSTr8XI"}, "href": "https://api.spotify.com/v1/artists/3ZJhC6cKBtTx6jUJSTr8XI", "id": "3ZJhC6cKBtTx6jUJSTr8XI", "name": "N\u00faria Graham", "type": "artist", "uri": "spotify:artist:3ZJhC6cKBtTx6jUJSTr8XI"}], "available_markets": [], "external_urls": {"spotify": "https://open.spotify.com/album/0s8lWLAIhWeKdeR9zDxNAm"}, "href": "https://api.spotify.com/v1/albums/0s8lWLAIhWeKdeR9zDxNAm", "id": "0s8lWLAIhWeKdeR9zDxNAm", "images": [{"url": "https://i.scdn.co/image/ab67616d0000b273db1ee65453e9c28ef3eb72dd", "width": 640, "height": 640}, {"url": "https://i.scdn.co/image/ab67616d00001e02db1ee65453e9c28ef3eb72dd", "width": 300, "height": 300}, {"url": "https://i.scdn.co/image/ab67616d00004851db1ee65453e9c28ef3eb72dd", "width": 64, "height": 64}], "name": "Bird Eyes", "release_date": "2015-03-02", "release_date_precision": "day", "total_tracks": 10, "type": "album", "uri": "spotify:album:0s8lWLAIhWeKdeR9zDxNAm"}, "artists": [{"external_urls": {"spotify": "https://open.spotify.com/artist/3ZJhC6cKBtTx6jUJSTr8XI"}, "href": "https://api.spotify.com/v1/artists/3ZJhC6cKBtTx6jUJSTr8XI", "id": "3ZJhC6cKBtTx6jUJSTr8XI", "name": "N\u00faria Graham", "type": "artist", "uri": "spotify:artist:3ZJhC6cKBtTx6jUJSTr8XI"}], "available_markets": [], "disc_number": 1, "duration_ms": 194278, "explicit": false, "external_ids": {"isrc": "ES66S1500038"}, "external_urls": {"spotify": "https://open.spotify.com/track/0Akzbjnami4YA8fKDrZOM6"}, "href": "https://api.spotify.com/v1/tracks/0Akzbjnami4YA8fKDrZOM6", "id": "0Akzbjnami4YA8fKDrZOM6", "is_local": false, "name": "Bad Luck", "popularity": 0, "preview_url": null, "track_number": 4, "type": "track", "uri": "spotify:track:0Akzbjnami4YA8fKDrZOM6"}