{"album": {"album_type": "album", "artists": [{"external_urls": {"spotify": "https://open.spotify.com/artist/7M1FPw29m5FbicYzS2xdpi"}, "href": "https://api.spotify.com/v1/artists/7M1FPw29m5FbicYzS2xdpi", "id": "7M1FPw29m5FbicYzS2xdpi", "name": "King Crimson", "type": "artist", "uri": "spotify:artist:7M1FPw29m5FbicYzS2xdpi"}], "available_markets": [], "external_urls": {"spotify": "https://open.spotify.com/album/6cGEJiBsNzLDDY1hoNgRQs"}, "href": "https://api.spotify.com/v1/albums/6cGEJiBsNzLDDY1hoNgRQs", "id": "6cGEJiBsNzLDDY1hoNgRQs", "images": [{"url": "https://i.scdn.co/image/ab67616d0000b273bc73d44df336487453124fbe", "width": 640, "height": 640}, {"url": "https://i.scdn.co/image/ab67616d00001e02bc73d44df336487453124fbe", "width": 300, "height": 300}, {"url": "https://i.scdn.co/image/ab67616d00004851bc73d44df336487453124fbe", "width": 64, "height": 64}], "name": "Islands", "release_date": "1971-12-03", "release_date_precision": "day", "total_tracks": 8, "type": "album", "uri": "spotify:album:6cGEJiBsNzLDDY1hoNgRQs"}, "artists": [{"external_urls": {"spotify": "https://open.spotify.com/artist/7M1FPw29m5FbicYzS2xdpi"}, "href": "https://api.spotify.com/v1/artists/7M1FPw29m5FbicYzS2xdpi", "id": "7M1FPw29m5FbicYzS2xdpi", "name": "King Crimson", "type": "artist", "uri": "spotify:artist:7M1FPw29m5FbicYzS2xdpi"}], "available_markets": [], "disc_number": 1, "duration_ms": 343703, "explicit": false, "external_ids": {"isrc": "GBCTX1500282"}, "external_urls": {"spotify": "https://open.spotify.com/track/3HTCIzvgNpiD7QnrFOU0TY"}, "href": "https://api.spotify.com/v1/tracks/3HTCIzvgNpiD7QnrFOU0TY", "id": "3HTCIzvgNpiD7QnrFOU0TY", "is_local": false, "name": "Ladies of the Road (Robert Fripp/David Singleton Remix)", "popularity": 0, "preview_url": null, "track_number": 8, "type": "track", "uri": "spotify:track:3HTCIzvgNpiD7QnrFOU0TY"}