{"album": {"album_type": "album", "artists": [{"external_urls": {"spotify": "https://open.spotify.com/artist/2ERWeFslDVHB4E9pSSw845"}, "href": "https://api.spotify.com/v1/artists/2ERWeFslDVHB4E9pSSw845", "id": "2ERWeFslDVHB4E9pSSw845", "name": "House of Shem", "type": "artist", "uri": "spotify:artist:2ERWeFslDVHB4E9pSSw845"}], "available_markets": [], "external_urls": {"spotify": "https://open.spotify.com/album/7lwuFsQxaQSKChdRmG74BY"}, "href": "https://api.spotify.com/v1/albums/7lwuFsQxaQSKChdRmG74BY", "id": "7lwuFsQxaQSKChdRmG74BY", "images": [{"url": "https://i.scdn.co/image/ab67616d0000b273e4cb2e7eba2b242d6ba4e8b3", "width": 640, "height": 640}, {"url": "https://i.scdn.co/image/ab67616d00001e02e4cb2e7eba2b242d6ba4e8b3", "width": 300, "height": 300}, {"url": "https://i.scdn.co/image/ab67616d00004851e4cb2e7eba2b242d6ba4e8b3", "width": 64, "height": 64}], "name": "Harmony", "release_date": "2014-01-28", "release_date_precision": "day", "total_tracks": 12, "type": "album", "uri": "spotify:album:7lwuFsQxaQSKChdRmG74BY"}, "artists": [{"external_urls": {"spotify": "https://open.spotify.com/artist/2ERWeFslDVHB4E9pSSw845"}, "href": "https://api.spotify.com/v1/artists/2ERWeFslDVHB4E9pSSw845", "id": "2ERWeFslDVHB4E9pSSw845", "name": "House of Shem", "type": "artist", "uri": "spotify:artist:2ERWeFslDVHB4E9pSSw845"}], "available_markets": [], "disc_number": 1, "duration_ms": 286386, "explicit": false, "external_ids": {"isrc": "USQY51416786"}, "external_urls": {"spotify": "https://open.spotify.com/track/6HuWGQK5Fb3f0rpjn7yBIA"}, "href": "https://api.spotify.com/v1/tracks/6HuWGQK5Fb3f0rpjn7yBIA", "id": "6HuWGQK5Fb3f0rpjn7yBIA", "is_local": false, "name": "Let It Be", "popularity": 0, "preview_url": null, "track_number": 10, "type": "track", "uri": "spotify:track:6HuWGQK5Fb3f0rpjn7yBIA"}