{"album": {"album_type": "album", "artists": [{"external_urls": {"spotify": "https://open.spotify.com/artist/0qvZjHbvW2o1kCbvXquWFW"}, "href": "https://api.spotify.com/v1/artists/0qvZjHbvW2o1kCbvXquWFW", "id": "0qvZjHbvW2o1kCbvXquWFW", "name": "Rossana Taddei", "type": "artist", "uri": "spotify:artist:0qvZjHbvW2o1kCbvXquWFW"}, {"external_urls": {"spotify": "https://open.spotify.com/artist/1V91O7M7AAOZxWnTRDlJy7"}, "href": "https://api.spotify.com/v1/artists/1V91O7M7AAOZxWnTRDlJy7", "id": "1V91O7M7AAOZxWnTRDlJy7", "name": "Leo Masl\u00edah", "type": "artist", "uri": "spotify:artist:1V91O7M7AAOZxWnTRDlJy7"}], "available_markets": ["AR", "AU", "AT", "BE", "BO", "BR", "BG", "CA", "CL", "CO", "CR", "CY", "CZ", "DK", "DO", "DE", "EC", "EE", "SV", "FI", "FR", "GR", "GT", "HN", "HK", "HU", "IS", "IE", "IT", "LV", "LT", "LU", "MY", "MT", "MX", "NL", "NZ", "NI", "NO", "PA", "PY", "PE", "PH", "PL", "PT", "SG", "SK", "ES", "SE", "CH", "TW", "TR", "UY", "US", "GB", "AD", "LI", "MC", "ID", "JP", "TH", "VN", "RO", "IL", "ZA", "SA", "AE", "BH", "QA", "OM", "KW", "EG", "MA", "DZ", "TN", "LB", "JO", "PS", "IN", "BY", "KZ", "MD", "UA", "AL", "BA", "HR", "ME", "MK", "RS", "SI", "KR", "BD", "PK", "LK", "GH", "KE", "NG", "TZ", "UG", "AG", "AM", "BS", "BB", "BZ", "BT", "BW", "BF", "CV", "CW", "DM", "FJ", "GM", "GE", "GD", "GW", "GY", "HT", "JM", "KI", "LS", "LR", "MW", "MV", "ML", "MH", "FM", "NA", "NR", "NE", "PW", "PG", "PR", "WS", "SM", "ST", "SN", "SC", "SL", "SB", "KN", "LC", "VC", "SR", "TL", "TO", "TT", "TV", "VU", "AZ", "BN", "BI", "KH", "CM", "TD", "KM", "GQ", "SZ", "GA", "GN", "KG", "LA", "MO", "MR", "MN", "NP", "RW", "TG", "UZ", "ZW", "BJ", "MG", "MU", "MZ", "AO", "CI", "DJ", "ZM", "CD", "CG", "IQ", "LY", "TJ", "VE", "ET", "XK"], "external_urls": {"spotify": "https://open.spotify.com/album/7yE09cgRzg04NkDxhnVbXc"}, "href": "https://api.spotify.com/v1/albums/7yE09cgRzg04NkDxhnVbXc", "id": "7yE09cgRzg04NkDxhnVbXc", "images": [{"url": "https://i.scdn.co/image/ab67616d0000b273338d9055f33b0f8d184410c5", "width": 640, "height": 640}, {"url": "https://i.scdn.co/image/ab67616d00001e02338d9055f33b0f8d184410c5", "width": 300, "height": 300}, {"url": "https://i.scdn.co/image/ab67616d00004851338d9055f33b0f8d184410c5", "width": 64, "height": 64}], "name": "Taddei Masl\u00edah", "release_date": "1997-08-01", "release_date_precision": "day", "total_tracks": 17, "type": "album", "uri": "spotify:album:7yE09cgRzg04NkDxhnVbXc"}, "artists": [{"external_urls": {"spotify": "https://open.spotify.com/artist/0qvZjHbvW2o1kCbvXquWFW"}, "href": "https://api.spotify.com/v1/artists/0qvZjHbvW2o1kCbvXquWFW", "id": "0qvZjHbvW2o1kCbvXquWFW", "name": "Rossana Taddei", "type": "artist", "uri": "spotify:artist:0qvZjHbvW2o1kCbvXquWFW"}, {"external_urls": {"spotify": "https://open.spotify.com/artist/1V91O7M7AAOZxWnTRDlJy7"}, "href": "https://api.spotify.com/v1/artists/1V91O7M7AAOZxWnTRDlJy7", "id": "1V91O7M7AAOZxWnTRDlJy7", "name": "Leo Masl\u00edah", "type": "artist", "uri": "spotify:artist:1V91O7M7AAOZxWnTRDlJy7"}, {"external_urls": {"spotify": "https://open.spotify.com/artist/0JyDgMUQZ2FR1VN8XGzoFJ"}, "href": "https://api.spotify.com/v1/artists/0JyDgMUQZ2FR1VN8XGzoFJ", "id": "0JyDgMUQZ2FR1VN8XGzoFJ", "name": "Jaime Roos", "type": "artist", "uri": "spotify:artist:0JyDgMUQZ2FR1VN8XGzoFJ"}, {"external_urls": {"spotify": "https://open.spotify.com/artist/5AfGpwSbYKelc5nJjUVRmb"}, "href": "https://api.spotify.com/v1/artists/5AfGpwSbYKelc5nJjUVRmb", "id": "5AfGpwSbYKelc5nJjUVRmb", "name": "Ruben Rada", "type": "artist", "uri": "spotify:artist:5AfGpwSbYKelc5nJjUVRmb"}, {"external_urls": {"spotify": "https://open.spotify.com/artist/1fGFX7G1T1xVqzjCtpini2"}, "href": "https://api.spotify.com/v1/artists/1fGFX7G1T1xVqzjCtpini2", "id": "1fGFX7G1T1xVqzjCtpini2", "name": "Fernando Cabrera", "type": "artist", "uri": "spotify:artist:1fGFX7G1T1xVqzjCtpini2"}, {"external_urls": {"spotify": "https://open.spotify.com/artist/42bSW87StWghA8hysIh96X"}, "href": "https://api.spotify.com/v1/artists/42bSW87StWghA8hysIh96X", "id": "42bSW87StWghA8hysIh96X", "name": "Samantha Navarro", "type": "artist", "uri": "spotify:artist:42bSW87StWghA8hysIh96X"}, {"external_urls": {"spotify": "https://open.spotify.com/artist/7nn8SAjbKT0CMqRyRhMpAh"}, "href": "https://api.spotify.com/v1/artists/7nn8SAjbKT0CMqRyRhMpAh", "id": "7nn8SAjbKT0CMqRyRhMpAh", "name": "Claudio Taddei", "type": "artist", "uri": "spotify:artist:7nn8SAjbKT0CMqRyRhMpAh"}, {"external_urls": {"spotify": "https://open.spotify.com/artist/5SU7A8zUc2besWu6gs0Ysi"}, "href": "https://api.spotify.com/v1/artists/5SU7A8zUc2besWu6gs0Ysi", "id": "5SU7A8zUc2besWu6gs0Ysi", "name": "Riki Musso", "type": "artist", "uri": "spotify:artist:5SU7A8zUc2besWu6gs0Ysi"}, {"external_urls": {"spotify": "https://open.spotify.com/artist/4Ifn9uMN0q9Gv6DEihwP6D"}, "href": "https://api.spotify.com/v1/artists/4Ifn9uMN0q9Gv6DEihwP6D", "id": "4Ifn9uMN0q9Gv6DEihwP6D", "name": "Jorge Schellemberg", "type": "artist", "uri": "spotify:artist:4Ifn9uMN0q9Gv6DEihwP6D"}], "available_markets": ["AR", "AU", "AT", "BE", "BO", "BR", "BG", "CA", "CL", "CO", "CR", "CY", "CZ", "DK", "DO", "DE", "EC", "EE", "SV", "FI", "FR", "GR", "GT", "HN", "HK", "HU", "IS", "IE", "IT", "LV", "LT", "LU", "MY", "MT", "MX", "NL", "NZ", "NI", "NO", "PA", "PY", "PE", "PH", "PL", "PT", "SG", "SK", "ES", "SE", "CH", "TW", "TR", "UY", "US", "GB", "AD", "LI", "MC", "ID", "JP", "TH", "VN", "RO", "IL", "ZA", "SA", "AE", "BH", "QA", "OM", "KW", "EG", "MA", "DZ", "TN", "LB", "JO", "PS", "IN", "BY", "KZ", "MD", "UA", "AL", "BA", "HR", "ME", "MK", "RS", "SI", "KR", "BD", "PK", "LK", "GH", "KE", "NG", "TZ", "UG", "AG", "AM", "BS", "BB", "BZ", "BT", "BW", "BF", "CV", "CW", "DM", "FJ", "GM", "GE", "GD", "GW", "GY", "HT", "JM", "KI", "LS", "LR", "MW", "MV", "ML", "MH", "FM", "NA", "NR", "NE", "PW", "PG", "PR", "WS", "SM", "ST", "SN", "SC", "SL", "SB", "KN", "LC", "VC", "SR", "TL", "TO", "TT", "TV", "VU", "AZ", "BN", "BI", "KH", "CM", "TD", "KM", "GQ", "SZ", "GA", "GN", "KG", "LA", "MO", "MR", "MN", "NP", "RW", "TG", "UZ", "ZW", "BJ", "MG", "MU", "MZ", "AO", "CI", "DJ", "ZM", "CD", "CG", "IQ", "LY", "TJ", "VE", "ET", "XK"], "disc_number": 1, "duration_ms": 157200, "explicit": false, "external_ids": {"isrc": "ARHXW2000010"}, "external_urls": {"spotify": "https://open.spotify.com/track/2pbDUOnytlOLltqIDEZAup"}, "href": "https://api.spotify.com/v1/tracks/2pbDUOnytlOLltqIDEZAup", "id": "2pbDUOnytlOLltqIDEZAup", "is_local": false, "name": "Blumenya", "popularity": 16, "preview_url": null, "track_number": 5, "type": "track", "uri": "spotify:track:2pbDUOnytlOLltqIDEZAup"}