{"album": {"album_type": "single", "artists": [{"external_urls": {"spotify": "https://open.spotify.com/artist/6HpIVA13SPof8sYuXRUfxj"}, "href": "https://api.spotify.com/v1/artists/6HpIVA13SPof8sYuXRUfxj", "id": "6HpIVA13SPof8sYuXRUfxj", "name": "Leyla Blue", "type": "artist", "uri": "spotify:artist:6HpIVA13SPof8sYuXRUfxj"}], "available_markets": [], "external_urls": {"spotify": "https://open.spotify.com/album/26UFiXXDkfoyFQoSar47vw"}, "href": "https://api.spotify.com/v1/albums/26UFiXXDkfoyFQoSar47vw", "id": "26UFiXXDkfoyFQoSar47vw", "images": [{"url": "https://i.scdn.co/image/ab67616d0000b273bcf44b2a6a937f841fbdef84", "width": 640, "height": 640}, {"url": "https://i.scdn.co/image/ab67616d00001e02bcf44b2a6a937f841fbdef84", "width": 300, "height": 300}, {"url": "https://i.scdn.co/image/ab67616d00004851bcf44b2a6a937f841fbdef84", "width": 64, "height": 64}], "name": "redbull", "release_date": "2024-03-20", "release_date_precision": "day", "total_tracks": 1, "type": "album", "uri": "spotify:album:26UFiXXDkfoyFQoSar47vw"}, "artists": [{"external_urls": {"spotify": "https://open.spotify.com/artist/6HpIVA13SPof8sYuXRUfxj"}, "href": "https://api.spotify.com/v1/artists/6HpIVA13SPof8sYuXRUfxj", "id": "6HpIVA13SPof8sYuXRUfxj", "name": "Leyla Blue", "type": "artist", "uri": "spotify:artist:6HpIVA13SPof8sYuXRUfxj"}], "available_markets": [], "disc_number": 1, "duration_ms": 140325, "explicit": false, "external_ids": {"isrc": "QM24S2401455"}, "external_urls": {"spotify": "https://open.spotify.com/track/7KNbwxbqXzXPWHJ8jbcG7o"}, "href": "https://api.spotify.com/v1/tracks/7KNbwxbqXzXPWHJ8jbcG7o", "id": "7KNbwxbqXzXPWHJ8jbcG7o", "is_local": false, "name": "redbull", "popularity": 0, "preview_url": null, "track_number": 1, "type": "track", "uri": "spotify:track:7KNbwxbqXzXPWHJ8jbcG7o"}