{"album": {"album_type": "album", "artists": [{"external_urls": {"spotify": "https://open.spotify.com/artist/3HrbmsYpKjWH1lzhad7alj"}, "href": "https://api.spotify.com/v1/artists/3HrbmsYpKjWH1lzhad7alj", "id": "3HrbmsYpKjWH1lzhad7alj", "name": "Los Aut\u00e9nticos Decadentes", "type": "artist", "uri": "spotify:artist:3HrbmsYpKjWH1lzhad7alj"}], "available_markets": [], "external_urls": {"spotify": "https://open.spotify.com/album/4WRgTB285z1AWwSSHtSOSL"}, "href": "https://api.spotify.com/v1/albums/4WRgTB285z1AWwSSHtSOSL", "id": "4WRgTB285z1AWwSSHtSOSL", "images": [{"url": "https://i.scdn.co/image/ab67616d0000b273d487fa9f7180ac3ce00f620f", "width": 640, "height": 640}, {"url": "https://i.scdn.co/image/ab67616d00001e02d487fa9f7180ac3ce00f620f", "width": 300, "height": 300}, {"url": "https://i.scdn.co/image/ab67616d00004851d487fa9f7180ac3ce00f620f", "width": 64, "height": 64}], "name": "Cualquiera Puede Cantar", "release_date": "1997", "release_date_precision": "year", "total_tracks": 15, "type": "album", "uri": "spotify:album:4WRgTB285z1AWwSSHtSOSL"}, "artists": [{"external_urls": {"spotify": "https://open.spotify.com/artist/3HrbmsYpKjWH1lzhad7alj"}, "href": "https://api.spotify.com/v1/artists/3HrbmsYpKjWH1lzhad7alj", "id": "3HrbmsYpKjWH1lzhad7alj", "name": "Los Aut\u00e9nticos Decadentes", "type": "artist", "uri": "spotify:artist:3HrbmsYpKjWH1lzhad7alj"}], "available_markets": [], "disc_number": 1, "duration_ms": 251733, "explicit": false, "external_ids": {"isrc": "ARF039703891"}, "external_urls": {"spotify": "https://open.spotify.com/track/4vsfgQsRmCaPmbon9Gb00f"}, "href": "https://api.spotify.com/v1/tracks/4vsfgQsRmCaPmbon9Gb00f", "id": "4vsfgQsRmCaPmbon9Gb00f", "is_local": false, "name": "Luna Radiante", "popularity": 0, "preview_url": null, "track_number": 4, "type": "track", "uri": "spotify:track:4vsfgQsRmCaPmbon9Gb00f"}