{"album": {"album_type": "album", "artists": [{"external_urls": {"spotify": "https://open.spotify.com/artist/2AbQwU2cuEGfD465wCXlg2"}, "href": "https://api.spotify.com/v1/artists/2AbQwU2cuEGfD465wCXlg2", "id": "2AbQwU2cuEGfD465wCXlg2", "name": "Rawayana", "type": "artist", "uri": "spotify:artist:2AbQwU2cuEGfD465wCXlg2"}], "available_markets": [], "external_urls": {"spotify": "https://open.spotify.com/album/3JwNymycAQq39DHeiqHUFm"}, "href": "https://api.spotify.com/v1/albums/3JwNymycAQq39DHeiqHUFm", "id": "3JwNymycAQq39DHeiqHUFm", "images": [{"url": "https://i.scdn.co/image/ab67616d0000b2734e12441423b20600d8d446f7", "width": 640, "height": 640}, {"url": "https://i.scdn.co/image/ab67616d00001e024e12441423b20600d8d446f7", "width": 300, "height": 300}, {"url": "https://i.scdn.co/image/ab67616d000048514e12441423b20600d8d446f7", "width": 64, "height": 64}], "name": "Trippy Caribbean", "release_date": "2016-10-07", "release_date_precision": "day", "total_tracks": 10, "type": "album", "uri": "spotify:album:3JwNymycAQq39DHeiqHUFm"}, "artists": [{"external_urls": {"spotify": "https://open.spotify.com/artist/2AbQwU2cuEGfD465wCXlg2"}, "href": "https://api.spotify.com/v1/artists/2AbQwU2cuEGfD465wCXlg2", "id": "2AbQwU2cuEGfD465wCXlg2", "name": "Rawayana", "type": "artist", "uri": "spotify:artist:2AbQwU2cuEGfD465wCXlg2"}, {"external_urls": {"spotify": "https://open.spotify.com/artist/2pvyE8W9RWESQxkyAWZqgY"}, "href": "https://api.spotify.com/v1/artists/2pvyE8W9RWESQxkyAWZqgY", "id": "2pvyE8W9RWESQxkyAWZqgY", "name": "Apache", "type": "artist", "uri": "spotify:artist:2pvyE8W9RWESQxkyAWZqgY"}], "available_markets": [], "disc_number": 1, "duration_ms": 286714, "explicit": false, "external_ids": {"isrc": "QZ5AB1607667"}, "external_urls": {"spotify": "https://open.spotify.com/track/2vg16RThWkdrrohdk4wq25"}, "href": "https://api.spotify.com/v1/tracks/2vg16RThWkdrrohdk4wq25", "id": "2vg16RThWkdrrohdk4wq25", "is_local": false, "name": "High", "popularity": 0, "preview_url": null, "track_number": 1, "type": "track", "uri": "spotify:track:2vg16RThWkdrrohdk4wq25"}