{"album": {"album_type": "album", "artists": [{"external_urls": {"spotify": "https://open.spotify.com/artist/2gClsBep1tt1rv1CN210SO"}, "href": "https://api.spotify.com/v1/artists/2gClsBep1tt1rv1CN210SO", "id": "2gClsBep1tt1rv1CN210SO", "name": "Gabriel Faur\u00e9", "type": "artist", "uri": "spotify:artist:2gClsBep1tt1rv1CN210SO"}, {"external_urls": {"spotify": "https://open.spotify.com/artist/6JSdWtNdhfjutA5r16UOpx"}, "href": "https://api.spotify.com/v1/artists/6JSdWtNdhfjutA5r16UOpx", "id": "6JSdWtNdhfjutA5r16UOpx", "name": "Eric Le Sage", "type": "artist", "uri": "spotify:artist:6JSdWtNdhfjutA5r16UOpx"}], "available_markets": ["AR", "BO", "BR", "BZ", "CA", "CL", "CO", "CR", "EC", "GT", "GY", "HN", "MX", "NI", "PA", "PE", "PY", "SR", "SV", "US", "UY", "VE"], "external_urls": {"spotify": "https://open.spotify.com/album/5SLjp0csHUJKdurX4qf7rg"}, "href": "https://api.spotify.com/v1/albums/5SLjp0csHUJKdurX4qf7rg", "id": "5SLjp0csHUJKdurX4qf7rg", "images": [{"url": "https://i.scdn.co/image/ab67616d0000b2739d2760786690ba2a141b98e8", "width": 640, "height": 640}, {"url": "https://i.scdn.co/image/ab67616d00001e029d2760786690ba2a141b98e8", "width": 300, "height": 300}, {"url": "https://i.scdn.co/image/ab67616d000048519d2760786690ba2a141b98e8", "width": 64, "height": 64}], "name": "Faur\u00e9: 4 - Duos et Trios avec Piano", "release_date": "2013-11-19", "release_date_precision": "day", "total_tracks": 23, "type": "album", "uri": "spotify:album:5SLjp0csHUJKdurX4qf7rg"}, "artists": [{"external_urls": {"spotify": "https://open.spotify.com/artist/2gClsBep1tt1rv1CN210SO"}, "href": "https://api.spotify.com/v1/artists/2gClsBep1tt1rv1CN210SO", "id": "2gClsBep1tt1rv1CN210SO", "name": "Gabriel Faur\u00e9", "type": "artist", "uri": "spotify:artist:2gClsBep1tt1rv1CN210SO"}, {"external_urls": {"spotify": "https://open.spotify.com/artist/6JSdWtNdhfjutA5r16UOpx"}, "href": "https://api.spotify.com/v1/artists/6JSdWtNdhfjutA5r16UOpx", "id": "6JSdWtNdhfjutA5r16UOpx", "name": "Eric Le Sage", "type": "artist", "uri": "spotify:artist:6JSdWtNdhfjutA5r16UOpx"}, {"external_urls": {"spotify": "https://open.spotify.com/artist/5HG9Eg7Ik8ZuNtMyGYTxLG"}, "href": "https://api.spotify.com/v1/artists/5HG9Eg7Ik8ZuNtMyGYTxLG", "id": "5HG9Eg7Ik8ZuNtMyGYTxLG", "name": "Alexandre Tharaud", "type": "artist", "uri": "spotify:artist:5HG9Eg7Ik8ZuNtMyGYTxLG"}], "available_markets": ["AR", "BO", "BR", "BZ", "CA", "CL", "CO", "CR", "EC", "GT", "GY", "HN", "MX", "NI", "PA", "PE", "PY", "SR", "SV", "US", "UY", "VE"], "disc_number": 1, "duration_ms": 140520, "explicit": false, "external_ids": {"isrc": "FR50X1260301"}, "external_urls": {"spotify": "https://open.spotify.com/track/1a7Z5exQ1nUBrCV4TV127U"}, "href": "https://api.spotify.com/v1/tracks/1a7Z5exQ1nUBrCV4TV127U", "id": "1a7Z5exQ1nUBrCV4TV127U", "is_local": false, "name": "Dolly, Op. 56 (version for piano 4 hands): I. Berceuse", "popularity": 33, "preview_url": null, "track_number": 1, "type": "track", "uri": "spotify:track:1a7Z5exQ1nUBrCV4TV127U"}