{"album": {"album_type": "compilation", "artists": [{"external_urls": {"spotify": "https://open.spotify.com/artist/2bmixwMZXlkl2sbIbOfviq"}, "href": "https://api.spotify.com/v1/artists/2bmixwMZXlkl2sbIbOfviq", "id": "2bmixwMZXlkl2sbIbOfviq", "name": "Bo Diddley", "type": "artist", "uri": "spotify:artist:2bmixwMZXlkl2sbIbOfviq"}], "available_markets": [], "external_urls": {"spotify": "https://open.spotify.com/album/10zuf7RQluaQGrbrXtU4nW"}, "href": "https://api.spotify.com/v1/albums/10zuf7RQluaQGrbrXtU4nW", "id": "10zuf7RQluaQGrbrXtU4nW", "images": [{"url": "https://i.scdn.co/image/ab67616d0000b273da43335e4901ccf00b9514fc", "width": 640, "height": 640}, {"url": "https://i.scdn.co/image/ab67616d00001e02da43335e4901ccf00b9514fc", "width": 300, "height": 300}, {"url": "https://i.scdn.co/image/ab67616d00004851da43335e4901ccf00b9514fc", "width": 64, "height": 64}], "name": "His Best", "release_date": "1997-01-01", "release_date_precision": "day", "total_tracks": 20, "type": "album", "uri": "spotify:album:10zuf7RQluaQGrbrXtU4nW"}, "artists": [{"external_urls": {"spotify": "https://open.spotify.com/artist/2bmixwMZXlkl2sbIbOfviq"}, "href": "https://api.spotify.com/v1/artists/2bmixwMZXlkl2sbIbOfviq", "id": "2bmixwMZXlkl2sbIbOfviq", "name": "Bo Diddley", "type": "artist", "uri": "spotify:artist:2bmixwMZXlkl2sbIbOfviq"}], "available_markets": [], "disc_number": 1, "duration_ms": 168000, "explicit": false, "external_ids": {"isrc": "USMC15547009"}, "external_urls": {"spotify": "https://open.spotify.com/track/1RB0enoqsqHElR3Pag8pzU"}, "href": "https://api.spotify.com/v1/tracks/1RB0enoqsqHElR3Pag8pzU", "id": "1RB0enoqsqHElR3Pag8pzU", "is_local": false, "name": "Bo Diddley", "popularity": 0, "preview_url": null, "track_number": 1, "type": "track", "uri": "spotify:track:1RB0enoqsqHElR3Pag8pzU"}