{"album": {"album_type": "album", "artists": [{"external_urls": {"spotify": "https://open.spotify.com/artist/1pVtwG5Up1OZOEpSHJ4AAs"}, "href": "https://api.spotify.com/v1/artists/1pVtwG5Up1OZOEpSHJ4AAs", "id": "1pVtwG5Up1OZOEpSHJ4AAs", "name": "Buddy Rich", "type": "artist", "uri": "spotify:artist:1pVtwG5Up1OZOEpSHJ4AAs"}], "available_markets": ["AR", "AU", "AT", "BE", "BO", "BR", "BG", "CA", "CL", "CO", "CR", "CY", "CZ", "DK", "DO", "DE", "EC", "EE", "SV", "FI", "FR", "GR", "GT", "HN", "HK", "HU", "IS", "IE", "IT", "LV", "LT", "LU", "MY", "MT", "MX", "NL", "NZ", "NI", "NO", "PA", "PY", "PE", "PH", "PL", "PT", "SG", "SK", "ES", "SE", "CH", "TW", "TR", "UY", "US", "GB", "AD", "LI", "MC", "ID", "JP", "TH", "VN", "RO", "IL", "ZA", "SA", "AE", "BH", "QA", "OM", "KW", "EG", "MA", "DZ", "TN", "LB", "JO", "PS", "IN", "BY", "KZ", "MD", "UA", "AL", "BA", "HR", "ME", "MK", "RS", "SI", "KR", "BD", "PK", "LK", "GH", "KE", "NG", "TZ", "UG", "AG", "AM", "BS", "BB", "BZ", "BT", "BW", "BF", "CV", "CW", "DM", "FJ", "GM", "GE", "GD", "GW", "GY", "HT", "JM", "KI", "LS", "LR", "MW", "MV", "ML", "MH", "FM", "NA", "NR", "NE", "PW", "PG", "WS", "SM", "ST", "SN", "SC", "SL", "SB", "KN", "LC", "VC", "SR", "TL", "TO", "TT", "TV", "VU", "AZ", "BN", "BI", "KH", "CM", "TD", "KM", "GQ", "SZ", "GA", "GN", "KG", "LA", "MO", "MR", "MN", "NP", "RW", "TG", "UZ", "ZW", "BJ", "MG", "MU", "MZ", "AO", "CI", "DJ", "ZM", "CD", "CG", "IQ", "LY", "TJ", "VE", "ET", "XK"], "external_urls": {"spotify": "https://open.spotify.com/album/3IhaI3Rp6vzENXQM5uokEo"}, "href": "https://api.spotify.com/v1/albums/3IhaI3Rp6vzENXQM5uokEo", "id": "3IhaI3Rp6vzENXQM5uokEo", "images": [{"url": "https://i.scdn.co/image/ab67616d0000b273a23dbe47879c19010f374e83", "width": 640, "height": 640}, {"url": "https://i.scdn.co/image/ab67616d00001e02a23dbe47879c19010f374e83", "width": 300, "height": 300}, {"url": "https://i.scdn.co/image/ab67616d00004851a23dbe47879c19010f374e83", "width": 64, "height": 64}], "name": "Big Swing Face (Live)", "release_date": "1967", "release_date_precision": "year", "total_tracks": 18, "type": "album", "uri": "spotify:album:3IhaI3Rp6vzENXQM5uokEo"}, "artists": [{"external_urls": {"spotify": "https://open.spotify.com/artist/5cyeaYQ80Wkqvxx4HcY0jo"}, "href": "https://api.spotify.com/v1/artists/5cyeaYQ80Wkqvxx4HcY0jo", "id": "5cyeaYQ80Wkqvxx4HcY0jo", "name": "Buddy Rich Big Band", "type": "artist", "uri": "spotify:artist:5cyeaYQ80Wkqvxx4HcY0jo"}], "available_markets": ["AR", "AU", "AT", "BE", "BO", "BR", "BG", "CA", "CL", "CO", "CR", "CY", "CZ", "DK", "DO", "DE", "EC", "EE", "SV", "FI", "FR", "GR", "GT", "HN", "HK", "HU", "IS", "IE", "IT", "LV", "LT", "LU", "MY", "MT", "MX", "NL", "NZ", "NI", "NO", "PA", "PY", "PE", "PH", "PL", "PT", "SG", "SK", "ES", "SE", "CH", "TW", "TR", "UY", "US", "GB", "AD", "LI", "MC", "ID", "JP", "TH", "VN", "RO", "IL", "ZA", "SA", "AE", "BH", "QA", "OM", "KW", "EG", "MA", "DZ", "TN", "LB", "JO", "PS", "IN", "BY", "KZ", "MD", "UA", "AL", "BA", "HR", "ME", "MK", "RS", "SI", "KR", "BD", "PK", "LK", "GH", "KE", "NG", "TZ", "UG", "AG", "AM", "BS", "BB", "BZ", "BT", "BW", "BF", "CV", "CW", "DM", "FJ", "GM", "GE", "GD", "GW", "GY", "HT", "JM", "KI", "LS", "LR", "MW", "MV", "ML", "MH", "FM", "NA", "NR", "NE", "PW", "PG", "WS", "SM", "ST", "SN", "SC", "SL", "SB", "KN", "LC", "VC", "SR", "TL", "TO", "TT", "TV", "VU", "AZ", "BN", "BI", "KH", "CM", "TD", "KM", "GQ", "SZ", "GA", "GN", "KG", "LA", "MO", "MR", "MN", "NP", "RW", "TG", "UZ", "ZW", "BJ", "MG", "MU", "MZ", "AO", "CI", "DJ", "ZM", "CD", "CG", "IQ", "LY", "TJ", "VE", "ET", "XK"], "disc_number": 1, "duration_ms": 306493, "explicit": false, "external_ids": {"isrc": "USBN29600737"}, "external_urls": {"spotify": "https://open.spotify.com/track/0gZ7AAs5ehEmfY3sXbuNq9"}, "href": "https://api.spotify.com/v1/tracks/0gZ7AAs5ehEmfY3sXbuNq9", "id": "0gZ7AAs5ehEmfY3sXbuNq9", "is_local": false, "name": "Bugle Call Rag - Live At Chez Club, Hollywood/1966/Remix", "popularity": 25, "preview_url": null, "track_number": 9, "type": "track", "uri": "spotify:track:0gZ7AAs5ehEmfY3sXbuNq9"}