{"album": {"album_type": "single", "artists": [{"external_urls": {"spotify": "https://open.spotify.com/artist/5pMCcLhPil65XVA7x0rRO1"}, "href": "https://api.spotify.com/v1/artists/5pMCcLhPil65XVA7x0rRO1", "id": "5pMCcLhPil65XVA7x0rRO1", "name": "Anand Wilder", "type": "artist", "uri": "spotify:artist:5pMCcLhPil65XVA7x0rRO1"}], "available_markets": [], "external_urls": {"spotify": "https://open.spotify.com/album/6fd1LCX7BMf2TmrhOYfD8r"}, "href": "https://api.spotify.com/v1/albums/6fd1LCX7BMf2TmrhOYfD8r", "id": "6fd1LCX7BMf2TmrhOYfD8r", "images": [{"url": "https://i.scdn.co/image/ab67616d0000b273563af0602b771188caa8e699", "width": 640, "height": 640}, {"url": "https://i.scdn.co/image/ab67616d00001e02563af0602b771188caa8e699", "width": 300, "height": 300}, {"url": "https://i.scdn.co/image/ab67616d00004851563af0602b771188caa8e699", "width": 64, "height": 64}], "name": "Delirium Passes", "release_date": "2021-09-24", "release_date_precision": "day", "total_tracks": 1, "type": "album", "uri": "spotify:album:6fd1LCX7BMf2TmrhOYfD8r"}, "artists": [{"external_urls": {"spotify": "https://open.spotify.com/artist/5pMCcLhPil65XVA7x0rRO1"}, "href": "https://api.spotify.com/v1/artists/5pMCcLhPil65XVA7x0rRO1", "id": "5pMCcLhPil65XVA7x0rRO1", "name": "Anand Wilder", "type": "artist", "uri": "spotify:artist:5pMCcLhPil65XVA7x0rRO1"}], "available_markets": [], "disc_number": 1, "duration_ms": 199014, "explicit": false, "external_ids": {"isrc": "CAL452100702"}, "external_urls": {"spotify": "https://open.spotify.com/track/39EIc8N8w1B302aqf1rmiC"}, "href": "https://api.spotify.com/v1/tracks/39EIc8N8w1B302aqf1rmiC", "id": "39EIc8N8w1B302aqf1rmiC", "is_local": false, "name": "Delirium Passes", "popularity": 0, "preview_url": null, "track_number": 1, "type": "track", "uri": "spotify:track:39EIc8N8w1B302aqf1rmiC"}