{"album": {"album_type": "compilation", "artists": [{"external_urls": {"spotify": "https://open.spotify.com/artist/0LyfQWJT6nXafLPZqxe9Of"}, "href": "https://api.spotify.com/v1/artists/0LyfQWJT6nXafLPZqxe9Of", "id": "0LyfQWJT6nXafLPZqxe9Of", "name": "Various Artists", "type": "artist", "uri": "spotify:artist:0LyfQWJT6nXafLPZqxe9Of"}], "available_markets": ["AR", "AU", "AT", "BE", "BO", "BR", "BG", "CA", "CL", "CO", "CR", "CY", "CZ", "DK", "DO", "DE", "EC", "EE", "SV", "FI", "FR", "GR", "GT", "HN", "HK", "HU", "IS", "IE", "IT", "LV", "LT", "LU", "MY", "MT", "MX", "NL", "NZ", "NI", "NO", "PA", "PY", "PE", "PH", "PL", "PT", "SG", "SK", "ES", "SE", "CH", "TW", "TR", "UY", "US", "GB", "AD", "LI", "MC", "ID", "TH", "VN", "RO", "IL", "ZA", "SA", "AE", "BH", "QA", "OM", "KW", "EG", "MA", "DZ", "TN", "LB", "JO", "PS", "IN", "KZ", "MD", "UA", "AL", "BA", "HR", "ME", "MK", "RS", "SI", "KR", "BD", "PK", "LK", "GH", "KE", "NG", "TZ", "UG", "AG", "AM", "BS", "BB", "BZ", "BT", "BW", "BF", "CV", "CW", "DM", "FJ", "GM", "GE", "GD", "GW", "GY", "HT", "JM", "KI", "LS", "LR", "MW", "MV", "ML", "MH", "FM", "NA", "NR", "NE", "PW", "PG", "WS", "SM", "ST", "SN", "SC", "SL", "SB", "KN", "LC", "VC", "SR", "TL", "TO", "TT", "TV", "VU", "AZ", "BN", "BI", "KH", "CM", "TD", "KM", "GQ", "SZ", "GA", "GN", "KG", "LA", "MO", "MR", "MN", "NP", "RW", "TG", "UZ", "ZW", "BJ", "MG", "MU", "MZ", "AO", "CI", "DJ", "ZM", "CD", "CG", "IQ", "LY", "TJ", "VE", "ET", "XK"], "external_urls": {"spotify": "https://open.spotify.com/album/4UKgY7QvwJwfEVqjYnOtVV"}, "href": "https://api.spotify.com/v1/albums/4UKgY7QvwJwfEVqjYnOtVV", "id": "4UKgY7QvwJwfEVqjYnOtVV", "images": [{"url": "https://i.scdn.co/image/ab67616d0000b27372a9e2fc35be84d62e044906", "width": 640, "height": 640}, {"url": "https://i.scdn.co/image/ab67616d00001e0272a9e2fc35be84d62e044906", "width": 300, "height": 300}, {"url": "https://i.scdn.co/image/ab67616d0000485172a9e2fc35be84d62e044906", "width": 64, "height": 64}], "name": "Moana/Vaiana/Oceania Multi-Language Songs, Vol. 1", "release_date": "2016-12-16", "release_date_precision": "day", "total_tracks": 117, "type": "album", "uri": "spotify:album:4UKgY7QvwJwfEVqjYnOtVV"}, "artists": [{"external_urls": {"spotify": "https://open.spotify.com/artist/2Z3wKK9BPJXctTjYx5RK6F"}, "href": "https://api.spotify.com/v1/artists/2Z3wKK9BPJXctTjYx5RK6F", "id": "2Z3wKK9BPJXctTjYx5RK6F", "name": "Celia Vergara", "type": "artist", "uri": "spotify:artist:2Z3wKK9BPJXctTjYx5RK6F"}, {"external_urls": {"spotify": "https://open.spotify.com/artist/0Lz17OpLni410OeMaUDFod"}, "href": "https://api.spotify.com/v1/artists/0Lz17OpLni410OeMaUDFod", "id": "0Lz17OpLni410OeMaUDFod", "name": "Amparo Bravo", "type": "artist", "uri": "spotify:artist:0Lz17OpLni410OeMaUDFod"}, {"external_urls": {"spotify": "https://open.spotify.com/artist/2H3XbexUEM1R4wLmUl1UQm"}, "href": "https://api.spotify.com/v1/artists/2H3XbexUEM1R4wLmUl1UQm", "id": "2H3XbexUEM1R4wLmUl1UQm", "name": "Jose Mar\u00eda Guzm\u00e1n", "type": "artist", "uri": "spotify:artist:2H3XbexUEM1R4wLmUl1UQm"}, {"external_urls": {"spotify": "https://open.spotify.com/artist/41sqYvXOn3ATsAQ65G1zx6"}, "href": "https://api.spotify.com/v1/artists/41sqYvXOn3ATsAQ65G1zx6", "id": "41sqYvXOn3ATsAQ65G1zx6", "name": "Mar\u00eda Parrado", "type": "artist", "uri": "spotify:artist:41sqYvXOn3ATsAQ65G1zx6"}, {"external_urls": {"spotify": "https://open.spotify.com/artist/0qtPxlxbzvu0jO7KgEtBey"}, "href": "https://api.spotify.com/v1/artists/0qtPxlxbzvu0jO7KgEtBey", "id": "0qtPxlxbzvu0jO7KgEtBey", "name": "Carlota de Santiago de Azc\u00e1rate", "type": "artist", "uri": "spotify:artist:0qtPxlxbzvu0jO7KgEtBey"}, {"external_urls": {"spotify": "https://open.spotify.com/artist/69kZvIUiXbQqJsXUOi7vwS"}, "href": "https://api.spotify.com/v1/artists/69kZvIUiXbQqJsXUOi7vwS", "id": "69kZvIUiXbQqJsXUOi7vwS", "name": "Aroa de Santiago de Azc\u00e1rate", "type": "artist", "uri": "spotify:artist:69kZvIUiXbQqJsXUOi7vwS"}], "available_markets": ["AR", "AU", "AT", "BE", "BO", "BR", "BG", "CA", "CL", "CO", "CR", "CY", "CZ", "DK", "DO", "DE", "EC", "EE", "SV", "FI", "FR", "GR", "GT", "HN", "HK", "HU", "IS", "IE", "IT", "LV", "LT", "LU", "MY", "MT", "MX", "NL", "NZ", "NI", "NO", "PA", "PY", "PE", "PH", "PL", "PT", "SG", "SK", "ES", "SE", "CH", "TW", "TR", "UY", "US", "GB", "AD", "LI", "MC", "ID", "TH", "VN", "RO", "IL", "ZA", "SA", "AE", "BH", "QA", "OM", "KW", "EG", "MA", "DZ", "TN", "LB", "JO", "PS", "IN", "KZ", "MD", "UA", "AL", "BA", "HR", "ME", "MK", "RS", "SI", "KR", "BD", "PK", "LK", "GH", "KE", "NG", "TZ", "UG", "AG", "AM", "BS", "BB", "BZ", "BT", "BW", "BF", "CV", "CW", "DM", "FJ", "GM", "GE", "GD", "GW", "GY", "HT", "JM", "KI", "LS", "LR", "MW", "MV", "ML", "MH", "FM", "NA", "NR", "NE", "PW", "PG", "WS", "SM", "ST", "SN", "SC", "SL", "SB", "KN", "LC", "VC", "SR", "TL", "TO", "TT", "TV", "VU", "AZ", "BN", "BI", "KH", "CM", "TD", "KM", "GQ", "SZ", "GA", "GN", "KG", "LA", "MO", "MR", "MN", "NP", "RW", "TG", "UZ", "ZW", "BJ", "MG", "MU", "MZ", "AO", "CI", "DJ", "ZM", "CD", "CG", "IQ", "LY", "TJ", "VE", "ET", "XK"], "disc_number": 1, "duration_ms": 210293, "explicit": false, "external_ids": {"isrc": "USWD11678020"}, "external_urls": {"spotify": "https://open.spotify.com/track/0UXw4YcStKCjhVdvnXZxSp"}, "href": "https://api.spotify.com/v1/tracks/0UXw4YcStKCjhVdvnXZxSp", "id": "0UXw4YcStKCjhVdvnXZxSp", "is_local": false, "name": "Aqu\u00ed est\u00e1 - De \"Vaiana\"/Banda Sonora Original en Castellano", "popularity": 35, "preview_url": null, "track_number": 31, "type": "track", "uri": "spotify:track:0UXw4YcStKCjhVdvnXZxSp"}