{"album": {"album_type": "single", "artists": [{"external_urls": {"spotify": "https://open.spotify.com/artist/3lLHpTOJ11tWiUNGYN14gt"}, "href": "https://api.spotify.com/v1/artists/3lLHpTOJ11tWiUNGYN14gt", "id": "3lLHpTOJ11tWiUNGYN14gt", "name": "Rejjie Snow", "type": "artist", "uri": "spotify:artist:3lLHpTOJ11tWiUNGYN14gt"}], "available_markets": [], "external_urls": {"spotify": "https://open.spotify.com/album/7ESc0SUNBXBlHv3h5MpBo0"}, "href": "https://api.spotify.com/v1/albums/7ESc0SUNBXBlHv3h5MpBo0", "id": "7ESc0SUNBXBlHv3h5MpBo0", "images": [{"url": "https://i.scdn.co/image/ab67616d0000b273644720e1fbdfa8a78769c72d", "width": 640, "height": 640}, {"url": "https://i.scdn.co/image/ab67616d00001e02644720e1fbdfa8a78769c72d", "width": 300, "height": 300}, {"url": "https://i.scdn.co/image/ab67616d00004851644720e1fbdfa8a78769c72d", "width": 64, "height": 64}], "name": "Blakkst Skn", "release_date": "2015-10-30", "release_date_precision": "day", "total_tracks": 1, "type": "album", "uri": "spotify:album:7ESc0SUNBXBlHv3h5MpBo0"}, "artists": [{"external_urls": {"spotify": "https://open.spotify.com/artist/3lLHpTOJ11tWiUNGYN14gt"}, "href": "https://api.spotify.com/v1/artists/3lLHpTOJ11tWiUNGYN14gt", "id": "3lLHpTOJ11tWiUNGYN14gt", "name": "Rejjie Snow", "type": "artist", "uri": "spotify:artist:3lLHpTOJ11tWiUNGYN14gt"}], "available_markets": [], "disc_number": 1, "duration_ms": 210563, "explicit": true, "external_ids": {"isrc": "USLGZ1500098"}, "external_urls": {"spotify": "https://open.spotify.com/track/3Hvexq1TWtvQxFvSzq26Ku"}, "href": "https://api.spotify.com/v1/tracks/3Hvexq1TWtvQxFvSzq26Ku", "id": "3Hvexq1TWtvQxFvSzq26Ku", "is_local": false, "name": "Blakkst Skn", "popularity": 0, "preview_url": null, "track_number": 1, "type": "track", "uri": "spotify:track:3Hvexq1TWtvQxFvSzq26Ku"}