{"audio_preview_url": "https://podz-content.spotifycdn.com/audio/clips/11nigPTMULRTFNCek7w5mA/clip_158110_218110.mp3", "description": "La negociaci\u00f3n pol\u00edtica y la b\u00fasqueda de financiaci\u00f3n del exterior. Existe una bomba de Leliq, ajuste y el peligro de una hiper recesi\u00f3n.", "duration_ms": 2420183, "explicit": false, "external_urls": {"spotify": "https://open.spotify.com/episode/6724262Ctg6hP7pPXf2R0m"}, "href": "https://api.spotify.com/v1/episodes/6724262Ctg6hP7pPXf2R0m", "html_description": "<p>La negociaci\u00f3n pol\u00edtica y la b\u00fasqueda de financiaci\u00f3n del exterior. Existe una bomba de Leliq, ajuste y el peligro de una hiper recesi\u00f3n.</p>", "id": "6724262Ctg6hP7pPXf2R0m", "images": [{"height": 640, "url": "https://i.scdn.co/image/ab6765630000ba8afb25f3905fe39945430d5c0b", "width": 640}, {"height": 300, "url": "https://i.scdn.co/image/ab67656300005f1ffb25f3905fe39945430d5c0b", "width": 300}, {"height": 64, "url": "https://i.scdn.co/image/ab6765630000f68dfb25f3905fe39945430d5c0b", "width": 64}], "is_externally_hosted": false, "is_playable": true, "language": "es-AR", "languages": ["es-AR"], "name": "La econom\u00eda de Milei", "release_date": "2023-11-29", "release_date_precision": "day", "show": {"available_markets": ["AD", "AE", "AG", "AL", "AM", "AO", "AR", "AT", "AU", "AZ", "BA", "BB", "BE", "BF", "BG", "BH", "BI", "BJ", "BN", "BO", "BR", "BS", "BT", "BW", "BZ", "CA", "CH", "CI", "CL", "CM", "CO", "CR", "CV", "CW", "CY", "CZ", "DE", "DJ", "DK", "DM", "DO", "DZ", "EC", "EE", "EG", "ES", "FI", "FJ", "FM", "FR", "GA", "GB", "GD", "GE", "GH", "GM", "GN", "GQ", "GR", "GT", "GW", "GY", "HK", "HN", "HR", "HT", "HU", "ID", "IE", "IL", "IN", "IS", "IT", "JM", "JO", "JP", "KE", "KH", "KI", "KM", "KN", "KR", "KW", "LA", "LB", "LC", "LI", "LR", "LS", "LT", "LU", "LV", "MA", "MC", "ME", "MG", "MH", "MK", "ML", "MN", "MO", "MR", "MT", "MU", "MV", "MW", "MX", "MY", "MZ", "NA", "NE", "NG", "NI", "NL", "NO", "NP", "NR", "NZ", "OM", "PA", "PE", "PG", "PH", "PL", "PR", "PS", "PT", "PW", "PY", "QA", "RO", "RS", "RW", "SA", "SB", "SC", "SE", "SG", "SI", "SK", "SL", "SM", "SN", "SR", "ST", "SV", "SZ", "TD", "TG", "TH", "TL", "TN", "TO", "TR", "TT", "TV", "TW", "TZ", "UA", "US", "UY", "UZ", "VC", "VN", "VU", "WS", "XK", "ZA", "ZM", "ZW"], "copyrights": [], "description": "Zaiat Ib\u00e1\u00f1ez  Programa de an\u00e1lisis pol\u00edtico y econ\u00f3mico de Argentina. Ib\u00e1\u00f1ez Zaiat", "explicit": false, "external_urls": {"spotify": "https://open.spotify.com/show/5NHjoNatpKoafg2HvdR7Wk"}, "href": "https://api.spotify.com/v1/shows/5NHjoNatpKoafg2HvdR7Wk", "html_description": "Zaiat Ib\u00e1\u00f1ez <br/>Programa de an\u00e1lisis pol\u00edtico y econ\u00f3mico de Argentina.<br/>Ib\u00e1\u00f1ez Zaiat", "id": "5NHjoNatpKoafg2HvdR7Wk", "images": [{"height": 640, "url": "https://i.scdn.co/image/ab6765630000ba8ac0629f433367cfa7c4bf7c56", "width": 640}, {"height": 300, "url": "https://i.scdn.co/image/ab67656300005f1fc0629f433367cfa7c4bf7c56", "width": 300}, {"height": 64, "url": "https://i.scdn.co/image/ab6765630000f68dc0629f433367cfa7c4bf7c56", "width": 64}], "is_externally_hosted": false, "languages": ["es-AR"], "media_type": "audio", "name": "Mano a Mano polp", "publisher": "FAP", "total_episodes": 73, "type": "show", "uri": "spotify:show:5NHjoNatpKoafg2HvdR7Wk"}, "type": "episode", "uri": "spotify:episode:6724262Ctg6hP7pPXf2R0m"}