{"album": {"album_type": "album", "artists": [{"external_urls": {"spotify": "https://open.spotify.com/artist/22bE4uQ6baNwSHPVcDxLCe"}, "href": "https://api.spotify.com/v1/artists/22bE4uQ6baNwSHPVcDxLCe", "id": "22bE4uQ6baNwSHPVcDxLCe", "name": "The Rolling Stones", "type": "artist", "uri": "spotify:artist:22bE4uQ6baNwSHPVcDxLCe"}], "available_markets": [], "external_urls": {"spotify": "https://open.spotify.com/album/4lzMSOfoyr3LsOuWeve5Cw"}, "href": "https://api.spotify.com/v1/albums/4lzMSOfoyr3LsOuWeve5Cw", "id": "4lzMSOfoyr3LsOuWeve5Cw", "images": [{"url": "https://i.scdn.co/image/ab67616d0000b2734149d0ee55ba8bb008011b4e", "width": 640, "height": 640}, {"url": "https://i.scdn.co/image/ab67616d00001e024149d0ee55ba8bb008011b4e", "width": 300, "height": 300}, {"url": "https://i.scdn.co/image/ab67616d000048514149d0ee55ba8bb008011b4e", "width": 64, "height": 64}], "name": "The Rolling Stones No. 2", "release_date": "1965-01-15", "release_date_precision": "day", "total_tracks": 12, "type": "album", "uri": "spotify:album:4lzMSOfoyr3LsOuWeve5Cw"}, "artists": [{"external_urls": {"spotify": "https://open.spotify.com/artist/22bE4uQ6baNwSHPVcDxLCe"}, "href": "https://api.spotify.com/v1/artists/22bE4uQ6baNwSHPVcDxLCe", "id": "22bE4uQ6baNwSHPVcDxLCe", "name": "The Rolling Stones", "type": "artist", "uri": "spotify:artist:22bE4uQ6baNwSHPVcDxLCe"}], "available_markets": [], "disc_number": 1, "duration_ms": 303186, "explicit": false, "external_ids": {"isrc": "USA176510010"}, "external_urls": {"spotify": "https://open.spotify.com/track/613moXqW8IxxagQk6pJ3od"}, "href": "https://api.spotify.com/v1/tracks/613moXqW8IxxagQk6pJ3od", "id": "613moXqW8IxxagQk6pJ3od", "is_local": false, "name": "Everybody Needs Somebody To Love - Long Version", "popularity": 0, "preview_url": null, "track_number": 1, "type": "track", "uri": "spotify:track:613moXqW8IxxagQk6pJ3od"}