{"album": {"album_type": "album", "artists": [{"external_urls": {"spotify": "https://open.spotify.com/artist/7j4EDoy89FLUbaeJuV1gNY"}, "href": "https://api.spotify.com/v1/artists/7j4EDoy89FLUbaeJuV1gNY", "id": "7j4EDoy89FLUbaeJuV1gNY", "name": "VILLAGR\u00c1N", "type": "artist", "uri": "spotify:artist:7j4EDoy89FLUbaeJuV1gNY"}], "available_markets": [], "external_urls": {"spotify": "https://open.spotify.com/album/0wfbIiCkr3Ew7lfT7yKgsV"}, "href": "https://api.spotify.com/v1/albums/0wfbIiCkr3Ew7lfT7yKgsV", "id": "0wfbIiCkr3Ew7lfT7yKgsV", "images": [{"url": "https://i.scdn.co/image/ab67616d0000b273e719e72743c5587124ea5ce4", "width": 640, "height": 640}, {"url": "https://i.scdn.co/image/ab67616d00001e02e719e72743c5587124ea5ce4", "width": 300, "height": 300}, {"url": "https://i.scdn.co/image/ab67616d00004851e719e72743c5587124ea5ce4", "width": 64, "height": 64}], "name": "El Ritmo Subtropical", "release_date": "2014-01-01", "release_date_precision": "day", "total_tracks": 12, "type": "album", "uri": "spotify:album:0wfbIiCkr3Ew7lfT7yKgsV"}, "artists": [{"external_urls": {"spotify": "https://open.spotify.com/artist/7j4EDoy89FLUbaeJuV1gNY"}, "href": "https://api.spotify.com/v1/artists/7j4EDoy89FLUbaeJuV1gNY", "id": "7j4EDoy89FLUbaeJuV1gNY", "name": "VILLAGR\u00c1N", "type": "artist", "uri": "spotify:artist:7j4EDoy89FLUbaeJuV1gNY"}], "available_markets": [], "disc_number": 1, "duration_ms": 332295, "explicit": false, "external_ids": {"isrc": "FR2X41749420"}, "external_urls": {"spotify": "https://open.spotify.com/track/2Z2D14j2sBdVtduoCJNbm0"}, "href": "https://api.spotify.com/v1/tracks/2Z2D14j2sBdVtduoCJNbm0", "id": "2Z2D14j2sBdVtduoCJNbm0", "is_local": false, "name": "Cae", "popularity": 0, "preview_url": null, "track_number": 12, "type": "track", "uri": "spotify:track:2Z2D14j2sBdVtduoCJNbm0"}