{"album": {"album_type": "album", "artists": [{"external_urls": {"spotify": "https://open.spotify.com/artist/0L2SCJoosQOW5BRqi9fEgL"}, "href": "https://api.spotify.com/v1/artists/0L2SCJoosQOW5BRqi9fEgL", "id": "0L2SCJoosQOW5BRqi9fEgL", "name": "D\u00fao Bote", "type": "artist", "uri": "spotify:artist:0L2SCJoosQOW5BRqi9fEgL"}, {"external_urls": {"spotify": "https://open.spotify.com/artist/6E68tprZpx0EA8mXQaUaQS"}, "href": "https://api.spotify.com/v1/artists/6E68tprZpx0EA8mXQaUaQS", "id": "6E68tprZpx0EA8mXQaUaQS", "name": "Abel Tesoriere", "type": "artist", "uri": "spotify:artist:6E68tprZpx0EA8mXQaUaQS"}, {"external_urls": {"spotify": "https://open.spotify.com/artist/4DT7C2ulb62pCMAKbGcl3j"}, "href": "https://api.spotify.com/v1/artists/4DT7C2ulb62pCMAKbGcl3j", "id": "4DT7C2ulb62pCMAKbGcl3j", "name": "Flor Bobadilla Oliva", "type": "artist", "uri": "spotify:artist:4DT7C2ulb62pCMAKbGcl3j"}], "available_markets": ["AR", "AU", "AT", "BE", "BO", "BR", "BG", "CA", "CL", "CO", "CR", "CY", "CZ", "DK", "DO", "DE", "EC", "EE", "SV", "FI", "FR", "GR", "GT", "HN", "HK", "HU", "IS", "IE", "IT", "LV", "LT", "LU", "MY", "MT", "MX", "NL", "NZ", "NI", "NO", "PA", "PY", "PE", "PH", "PL", "PT", "SG", "SK", "ES", "SE", "CH", "TW", "TR", "UY", "US", "GB", "AD", "LI", "MC", "ID", "JP", "TH", "VN", "RO", "IL", "ZA", "SA", "AE", "BH", "QA", "OM", "KW", "EG", "MA", "DZ", "TN", "LB", "JO", "PS", "IN", "BY", "KZ", "MD", "UA", "AL", "BA", "HR", "ME", "MK", "RS", "SI", "KR", "BD", "PK", "LK", "GH", "KE", "NG", "TZ", "UG", "AG", "AM", "BS", "BB", "BZ", "BT", "BW", "BF", "CV", "CW", "DM", "FJ", "GM", "GE", "GD", "GW", "GY", "HT", "JM", "KI", "LS", "LR", "MW", "MV", "ML", "MH", "FM", "NA", "NR", "NE", "PW", "PG", "PR", "WS", "SM", "ST", "SN", "SC", "SL", "SB", "KN", "LC", "VC", "SR", "TL", "TO", "TT", "TV", "VU", "AZ", "BN", "BI", "KH", "CM", "TD", "KM", "GQ", "SZ", "GA", "GN", "KG", "LA", "MO", "MR", "MN", "NP", "RW", "TG", "UZ", "ZW", "BJ", "MG", "MU", "MZ", "AO", "CI", "DJ", "ZM", "CD", "CG", "IQ", "LY", "TJ", "VE", "ET", "XK"], "external_urls": {"spotify": "https://open.spotify.com/album/6YCvmX5LGwqomhb1xXjmQn"}, "href": "https://api.spotify.com/v1/albums/6YCvmX5LGwqomhb1xXjmQn", "id": "6YCvmX5LGwqomhb1xXjmQn", "images": [{"url": "https://i.scdn.co/image/ab67616d0000b2732b9edc4c947ba405534f27d5", "width": 640, "height": 640}, {"url": "https://i.scdn.co/image/ab67616d00001e022b9edc4c947ba405534f27d5", "width": 300, "height": 300}, {"url": "https://i.scdn.co/image/ab67616d000048512b9edc4c947ba405534f27d5", "width": 64, "height": 64}], "name": "Ysyry", "release_date": "2015-10-22", "release_date_precision": "day", "total_tracks": 11, "type": "album", "uri": "spotify:album:6YCvmX5LGwqomhb1xXjmQn"}, "artists": [{"external_urls": {"spotify": "https://open.spotify.com/artist/0L2SCJoosQOW5BRqi9fEgL"}, "href": "https://api.spotify.com/v1/artists/0L2SCJoosQOW5BRqi9fEgL", "id": "0L2SCJoosQOW5BRqi9fEgL", "name": "D\u00fao Bote", "type": "artist", "uri": "spotify:artist:0L2SCJoosQOW5BRqi9fEgL"}, {"external_urls": {"spotify": "https://open.spotify.com/artist/6E68tprZpx0EA8mXQaUaQS"}, "href": "https://api.spotify.com/v1/artists/6E68tprZpx0EA8mXQaUaQS", "id": "6E68tprZpx0EA8mXQaUaQS", "name": "Abel Tesoriere", "type": "artist", "uri": "spotify:artist:6E68tprZpx0EA8mXQaUaQS"}, {"external_urls": {"spotify": "https://open.spotify.com/artist/4DT7C2ulb62pCMAKbGcl3j"}, "href": "https://api.spotify.com/v1/artists/4DT7C2ulb62pCMAKbGcl3j", "id": "4DT7C2ulb62pCMAKbGcl3j", "name": "Flor Bobadilla Oliva", "type": "artist", "uri": "spotify:artist:4DT7C2ulb62pCMAKbGcl3j"}], "available_markets": ["AR", "AU", "AT", "BE", "BO", "BR", "BG", "CA", "CL", "CO", "CR", "CY", "CZ", "DK", "DO", "DE", "EC", "EE", "SV", "FI", "FR", "GR", "GT", "HN", "HK", "HU", "IS", "IE", "IT", "LV", "LT", "LU", "MY", "MT", "MX", "NL", "NZ", "NI", "NO", "PA", "PY", "PE", "PH", "PL", "PT", "SG", "SK", "ES", "SE", "CH", "TW", "TR", "UY", "US", "GB", "AD", "LI", "MC", "ID", "JP", "TH", "VN", "RO", "IL", "ZA", "SA", "AE", "BH", "QA", "OM", "KW", "EG", "MA", "DZ", "TN", "LB", "JO", "PS", "IN", "BY", "KZ", "MD", "UA", "AL", "BA", "HR", "ME", "MK", "RS", "SI", "KR", "BD", "PK", "LK", "GH", "KE", "NG", "TZ", "UG", "AG", "AM", "BS", "BB", "BZ", "BT", "BW", "BF", "CV", "CW", "DM", "FJ", "GM", "GE", "GD", "GW", "GY", "HT", "JM", "KI", "LS", "LR", "MW", "MV", "ML", "MH", "FM", "NA", "NR", "NE", "PW", "PG", "PR", "WS", "SM", "ST", "SN", "SC", "SL", "SB", "KN", "LC", "VC", "SR", "TL", "TO", "TT", "TV", "VU", "AZ", "BN", "BI", "KH", "CM", "TD", "KM", "GQ", "SZ", "GA", "GN", "KG", "LA", "MO", "MR", "MN", "NP", "RW", "TG", "UZ", "ZW", "BJ", "MG", "MU", "MZ", "AO", "CI", "DJ", "ZM", "CD", "CG", "IQ", "LY", "TJ", "VE", "ET", "XK"], "disc_number": 1, "duration_ms": 159660, "explicit": false, "external_ids": {"isrc": "QMFMG1521366"}, "external_urls": {"spotify": "https://open.spotify.com/track/7xsgMr9nMvh5eKkuFOsGVL"}, "href": "https://api.spotify.com/v1/tracks/7xsgMr9nMvh5eKkuFOsGVL", "id": "7xsgMr9nMvh5eKkuFOsGVL", "is_local": false, "name": "Ndeve Guara Santan\u00ed", "popularity": 11, "preview_url": null, "track_number": 3, "type": "track", "uri": "spotify:track:7xsgMr9nMvh5eKkuFOsGVL"}